nonebot_plugin_nailongremove/__init__.py
nonebot_plugin_nailongremove/config.py
nonebot_plugin_nailongremove/frame_source.py
nonebot_plugin_nailongremove/handler.py
nonebot_plugin_nailongremove/model/__init__.py
nonebot_plugin_nailongremove/model/classification.py
nonebot_plugin_nailongremove/model/hf_detection.py
nonebot_plugin_nailongremove/model/target_detection.py
nonebot_plugin_nailongremove/model/utils/__init__.py
nonebot_plugin_nailongremove/model/utils/common.py
nonebot_plugin_nailongremove/model/utils/update.py
nonebot_plugin_nailongremove/model/utils/yolox.py
nonebot_plugin_nailongremove/uniapi/__init__.py
nonebot_plugin_nailongremove/uniapi/mute.py
nonebot_plugin_nailongremove/uniapi/recall.py
nonebot_plugin_nailongremove_base-2.3.6.post3.dist-info/METADATA
nonebot_plugin_nailongremove_base-2.3.6.post3.dist-info/WHEEL
nonebot_plugin_nailongremove_base-2.3.6.post3.dist-info/entry_points.txt
nonebot_plugin_nailongremove_base-2.3.6.post3.dist-info/RECORD
