Metadata-Version: 2.1
Name: nonebot-plugin-nailongremove-base
Version: 2.3.6.post3
Summary: 识别目标并撤回图片插件
Keywords: nonebot,plugin,image
Author-Email: 445 <2877834692@qq.com>, student_2333 <lgc2333@126.com>
License: MIT
Project-URL: homepage, https://github.com/superbot-ai445/nonebot-plugin-nailongremove
Project-URL: repository, https://github.com/superbot-ai445/nonebot-plugin-nailongremove
Requires-Python: <4.0,>=3.9
Requires-Dist: nonebot2>=2.2.0
Requires-Dist: nonebot-plugin-alconna>=0.53.1
Requires-Dist: nonebot-plugin-uninfo>=0.5.0
Requires-Dist: opencv-python>=4.5
Requires-Dist: numpy>=1.19
Requires-Dist: pillow>=9
Requires-Dist: cookit[pydantic]>=0.8.1
Requires-Dist: httpx>=0.27.2
Requires-Dist: githubkit>=0.11.14
Requires-Dist: yarl>=1.17.1
Requires-Dist: tqdm>=4.66.6
Requires-Dist: huggingface-hub>=0.26.2
Requires-Dist: ultralytics>=8.3.31
Requires-Dist: gradio-client>=1.3.0
Requires-Dist: faiss-cpu>=1.9.0.post1
Requires-Dist: scikit-learn>=1.5.2
